{
	"Name" : "FantasyNamesIndex",
	"Title" : "Fantasy Name Generator Index",	
	"Dependencies" : "",
	"ButtonText" : "Hide",
	"Type" : "Content",
	
	"Data" : {
		"1" : {
			"Text" : "<h3>Generic Fantasy</h3>"
		},
		"2" : { 
			"TextIndex" : [
                {"Dark-Elf":"?gen=Names/Fantasy/DarkElf"},
                {"Dwarven":"?gen=Names/Fantasy/Dwarf"},
                {"High-Elf":"?gen=Names/Fantasy/HighElf"},
                {"Human":"?gen=Names/Fantasy/Human"},
                {"Orcish":"?gen=Names/Fantasy/Orc"},
                {"Wood-Elf":"?gen=Names/Fantasy/WoodElf"}
			],
            "ParagraphType" : "DoubleIndex" 
		},
        "3" : {
			"Text" : "<h3>Miscellaneous</h3>"
		},
		"4" : { 
			"TextIndex" : [
				{"Wuxia Inspired":"?gen=Names/Fantasy/Wuxia"}
			],
            "ParagraphType" : "DoubleIndex" 
		}
	}
}