{
    "Name" : "GenericDarkElfFantasyNameFamily",
    "Type" : "Table",    
    "Data": {
        "1": [
            {"Alabaster":1},
            {"Black":1},
            {"Blight":1},
            {"Cave":1},
            {"Charcoal":1},
            {"Chill":1},
            {"Clear":1},
            {"Cloud":1},
            {"Crow":1},
            {"Cruel":1},
            {"Dark":1},
            {"Day":1},
            {"Dim":1},
            {"Ebony":1},
            {"Eclipse":1},
            {"Empty":1},
            {"Freeze":1},
            {"Frost":1},
            {"Gloom":1},
            {"Hoar":1},
            {"Ice":1},
            {"Ink":1},
            {"Ivory":1},
            {"Luna":1},
            {"Midnight":1},
            {"Moon":1},
            {"Nadir":1},
            {"Needle":1},
            {"Night":1},
            {"Obsidian":1},
            {"Onyx":1},
            {"Pallid":1},
            {"Pearl":1},
            {"Pitch":1},
            {"Poison":1},
            {"Raven":1},
            {"Rime":1},
            {"Sable":1},
            {"Sharp":1},
            {"Silent":1},
            {"Silver":1},
            {"Sleet":1},
            {"Snow":1},
            {"Soot":1},
            {"Star":1},
            {"Venom":1},
            {"Vernal":1},
            {"Void":1},
            {"Whisper":1},
            {"Winter":1}   
        ],
         "2": [
            {"arrow":1},
            {"bare":1},
            {"beak":1},
            {"blade":1},
            {"bleed":1},
            {"blood":1},
            {"break":1},
            {"claw":1},
            {"cloak":1},
            {"crest":1},
            {"cut":1},
            {"dew":1},
            {"end":1},
            {"fang":1},
            {"feather":1},
            {"front":1},
            {"guard":1},
            {"hair":1},
            {"iron":1},
            {"lance":1},
            {"lid":1},
            {"mane":1},
            {"mask":1},
            {"pain":1},
            {"pride":1},
            {"rage":1},
            {"runner":1},
            {"seeker":1},
            {"shadow":1},
            {"shard":1},
            {"shave":1},
            {"sheath":1},
            {"shock":1},
            {"shot":1},
            {"skin":1},
            {"sky":1},
            {"speaker":1},
            {"spear":1},
            {"spy":1},
            {"steel":1},
            {"streak":1},
            {"strike":1},
            {"stripe":1},
            {"sword":1},
            {"tail":1},
            {"tress":1},
            {"vault":1},
            {"veil":1},
            {"veneer":1},
            {"whip":1}    
        ]
    }
}